LICENSE
README.md
setup.py
uptime_kuma_api/__init__.py
uptime_kuma_api/__version__.py
uptime_kuma_api/api.py
uptime_kuma_api/auth_method.py
uptime_kuma_api/docker_type.py
uptime_kuma_api/docstrings.py
uptime_kuma_api/event.py
uptime_kuma_api/exceptions.py
uptime_kuma_api/incident_style.py
uptime_kuma_api/maintenance_strategy.py
uptime_kuma_api/monitor_status.py
uptime_kuma_api/monitor_type.py
uptime_kuma_api/notification_providers.py
uptime_kuma_api/proxy_protocol.py
uptime_kuma_api.egg-info/PKG-INFO
uptime_kuma_api.egg-info/SOURCES.txt
uptime_kuma_api.egg-info/dependency_links.txt
uptime_kuma_api.egg-info/requires.txt
uptime_kuma_api.egg-info/top_level.txt